heatmap_digitizer/__init__.py
heatmap_digitizer/__main__.py
heatmap_digitizer/heatmap_digitizer.py
heatmap_digitizer/data/example.png
heatmap_digitizer-0.1.0.dist-info/LICENSE
heatmap_digitizer-0.1.0.dist-info/METADATA
heatmap_digitizer-0.1.0.dist-info/WHEEL
heatmap_digitizer-0.1.0.dist-info/top_level.txt
heatmap_digitizer-0.1.0.dist-info/RECORD
